fiphopha/__init__.py
fiphopha/between_bootstrap.py
fiphopha/downsampler.py
fiphopha/run_fiphopha.py
fiphopha/timebins.py
fiphopha/within_bootstrap.py
fiphopha-0.2.1.dist-info/licenses/LICENSE.md
fiphopha-0.2.1.dist-info/METADATA
fiphopha-0.2.1.dist-info/WHEEL
fiphopha-0.2.1.dist-info/entry_points.txt
fiphopha-0.2.1.dist-info/top_level.txt
fiphopha-0.2.1.dist-info/RECORD
