Metadata-Version: 2.4
Name: fiphopha
Version: 0.2.1
Summary: FiPhoPHA - A fiber photometry Python package for post-hoc analysis
Home-page: https://github.com/VasiliDrakopoulos/fiphopha
Author: Vasilios Drakopoulos
Author-email: Vasilios.Drakopoulos@monash.edu
License: MIT
Classifier: Programming Language :: Python
Classifier: Operating System :: OS Independent
Requires-Python: >=3.7
License-File: LICENSE.md
Requires-Dist: numpy
Requires-Dist: pandas
Requires-Dist: scikit-learn
Requires-Dist: tk
Requires-Dist: setuptools
Requires-Dist: openpyxl
Dynamic: author
Dynamic: author-email
Dynamic: classifier
Dynamic: description
Dynamic: description-content-type
Dynamic: home-page
Dynamic: license
Dynamic: license-file
Dynamic: requires-dist
Dynamic: requires-python
Dynamic: summary
